oceandb_mongodb_driver/__init__.py
oceandb_mongodb_driver/indexes.py
oceandb_mongodb_driver/instance.py
oceandb_mongodb_driver/plugin.py
oceandb_mongodb_driver/utils.py
oceandb_mongodb_driver-0.2.2.dist-info/LICENSE
oceandb_mongodb_driver-0.2.2.dist-info/METADATA
oceandb_mongodb_driver-0.2.2.dist-info/WHEEL
oceandb_mongodb_driver-0.2.2.dist-info/top_level.txt
oceandb_mongodb_driver-0.2.2.dist-info/RECORD
