Metadata-Version: 2.1
Name: oceandb-mongodb-driver
Version: 0.2.2
Summary: 🐳 Mongo DB BigchainDB driver (Python).
Home-page: https://github.com/oceanprotocol/oceandb-mongodb-driver
Author: leucothia
Author-email: devops@oceanprotocol.com
License: Apache Software License 2.0
Keywords: oceandb-mongodb-driver
Platform: UNKNOWN
Classifier: Development Status :: 2 - Pre-Alpha
Classifier: Intended Audience :: Developers
Classifier: License :: OSI Approved :: Apache Software License
Classifier: Natural Language :: English
Classifier: Programming Language :: Python :: 3.4
Classifier: Programming Language :: Python :: 3.5
Classifier: Programming Language :: Python :: 3.6
Requires-Dist: oceandb-driver-interface
Requires-Dist: pymongo
